todolist_lb_me_ab/Tache.py
todolist_lb_me_ab/__init__.py
todolist_lb_me_ab/todolist.py
todolist_lb_me_ab-1.0.1.dist-info/METADATA
todolist_lb_me_ab-1.0.1.dist-info/WHEEL
todolist_lb_me_ab-1.0.1.dist-info/entry_points.txt
todolist_lb_me_ab-1.0.1.dist-info/RECORD
