Metadata-Version: 2.1
Name: todolist_lb_me_ab
Version: 1.0.1
Summary: 
Author: Leo Barberis
Author-email: leo.barberis@telecom-paris.fr
Requires-Python: >=3.10.12
Classifier: Programming Language :: Python :: 3
Classifier: Programming Language :: Python :: 3.11
